luigino/__init__.py
luigino/cleanup.py
luigino/common_task.py
luigino/errorlog.py
luigino/execute.py
luigino-0.1.5.dist-info/METADATA
luigino-0.1.5.dist-info/WHEEL
luigino-0.1.5.dist-info/top_level.txt
luigino-0.1.5.dist-info/RECORD
