Metadata-Version: 2.1
Name: luigino
Version: 0.1.5
Summary: Utilities package for Luigi tasks with Celery integration
Home-page: https://github.com/jyjung/luigino
Author: Jung JinYoung
Author-email: bungker@gmail.com
Classifier: Programming Language :: Python :: 3
Classifier: License :: OSI Approved :: MIT License
Classifier: Operating System :: OS Independent
Requires-Python: >=3.7
Requires-Dist: luigi
Requires-Dist: celery
